{
  "id": "havo_geschiedenis_2023_t1_q04",
  "metadata": {
    "exam": {
      "education_level": "havo",
      "discipline": "geschiedenis",
      "year": 2023,
      "tijdvak": 1
    },
    "curriculum": {
      "education_level_discipline_id": 29,
      "domains": [],
      "subdomains": [
        {
          "id": 197,
          "name": "Tijdvak 5 – Ontdekkers en hervormers",
          "prefix_code": 5
        }
      ],
      "sub_learning_objective_ids": []
    }
  },
  "question": {
    "text": "<p>Toon aan, telkens met een verwijzing naar de prent, dat De Champlain:</p><ul><li>zijn benoeming als vicegouverneur rechtvaardigt, en</li><li>de waarschuwing geeft dat de Franse belangen in Amerika gevaar Iopen.</li></ul>",
    "max_score": 2,
    "is_self_scored": false
  },
  "solution": {
    "text": "",
    "image": null
  },
  "content_context": [
    {
      "order": 0,
      "type": "text",
      "text": "<p>Gebruik bron 1.<br>Een conclusie:<br>De Europese overzeese expansie draagt bij aan het veranderende mens- en wereldbeeld van de renaissance.</p>"
    },
    {
      "order": 1,
      "type": "text",
      "text": "<p>In 1594 gaf generaal Willem Lodewijk van Nassau-Dillenburg aan de opperbevelhebber van het leger van de Republiek het advies om 'de contramars' in te voeren. Dit was een methode waardoor soldaten sneller klaarstonden voor de aanval. Willem Lodewijk had over de contramars gelezen in het boek <i>Tactische theorie</i> van de Griekse schrijver Aelianus uit de tweede eeuw.</p>"
    },
    {
      "order": 2,
      "type": "text",
      "text": "<p><i>Gebruik bron 2.</i></p><p>De Champlain publiceert het boek Reizen kort na zijn benoeming als vicegouverneur van de Franse kolonie in Amerika.</p>"
    }
  ],
  "bijlages": [
    {
      "name": "Geschiedenis 2023 I_bijlage.pdf",
      "media_path": "media/bijlages/Geschiedenis_2023_I_bijlage_2ccfd292fdea.pdf",
      "azure_url": "https://bbprodpublicsa.blob.core.windows.net/public/55cb39c4e0dc4b628a1ed42d2c5ca13a.pdf"
    }
  ]
}