{
  "id": "vwo_spaans_2025_t1_q27",
  "metadata": {
    "exam": {
      "education_level": "vwo",
      "discipline": "spaans",
      "year": 2025,
      "tijdvak": 1
    },
    "curriculum": {
      "education_level_discipline_id": 19,
      "domains": [],
      "subdomains": [],
      "sub_learning_objective_ids": []
    }
  },
  "question": {
    "text": "<p>Lee el párrafo 5 .<br>¿Qué pregunta falta en la línea 40 ?<br>A ¿Qué consejos daría a sus lectores?<br>B ¿Qué dudas ha tenido al escribir sus novelas?<br>C ¿Qué lecciones ha aprendido como escritor?<br>D ¿Qué motivos tiene el público para apreciar tanto sus libros?</p>",
    "max_score": 1,
    "is_self_scored": false
  },
  "solution": {
    "text": "",
    "image": null
  },
  "content_context": [],
  "bijlages": [
    {
      "name": "vw-1005-a-25-1-b.pdf",
      "media_path": "media/bijlages/vw-1005-a-25-1-b_9179e3584a31.pdf",
      "azure_url": "https://bbprodpublicsa.blob.core.windows.net/public/91d4d7d08fc340209edfd5208c543de0.pdf"
    }
  ]
}