{
  "id": "havo_biologie_2021_t1_q36",
  "metadata": {
    "exam": {
      "education_level": "havo",
      "discipline": "biologie",
      "year": 2021,
      "tijdvak": 1
    },
    "curriculum": {
      "education_level_discipline_id": 32,
      "domains": [],
      "subdomains": [
        {
          "id": 121,
          "name": "Stofwisseling van de cel",
          "prefix_code": 2
        },
        {
          "id": 125,
          "name": "Stofwisseling van het organisme",
          "prefix_code": 1
        },
        {
          "id": 126,
          "name": "Zelfregulatie van het organisme",
          "prefix_code": 2
        },
        {
          "id": 127,
          "name": "Afweer van het organisme",
          "prefix_code": 3
        }
      ],
      "sub_learning_objective_ids": []
    }
  },
  "question": {
    "text": "<p>Verklaar waardoor speekselenzymen het zetmeel in de maag niet kunnen verteren.</p>",
    "max_score": 1,
    "is_self_scored": false
  },
  "solution": {
    "text": "",
    "image": null
  },
  "content_context": [
    {
      "order": 0,
      "type": "text",
      "text": "<p>Maranja is een meisje van bijna twee jaar oud met het 18p-tetrasomiesyndroom. Door haar ontwikkelingsachterstand heeft Maranja veel zorg nodig.</p><p>18p-tetrasomie is een zeldzame afwijking waarbij elke lichaamscel naast de normale set chromosomen een extra chromosoom bevat. Dit extra chromosoom (i18p) bestaat uit twee keer de korte arm van chromosoom 18 (afbeelding 1).</p>"
    },
    {
      "order": 1,
      "type": "image",
      "media_path": "media/in-exam/img_2c4f8dbd1489.png",
      "azure_url": "https://bbprodpublicsa.blob.core.windows.net/public/6b6e88e44b184deda90ca533b892571e.png",
      "caption": ""
    },
    {
      "order": 2,
      "type": "text",
      "text": "<p>Een aantal genen komt hierdoor vier keer voor in elke cel. Dit verstoort de aanleg van organen tijdens de ontwikkeling van het kind in de baarmoeder.</p><p>De diagnose 18p-tetrasomiesyndroom werd bij Maranja bevestigd door haar karyotype te bepalen uit een karyogram. Het karyotype beschrijft per lichaamscel het totale aantal chromosomen, de geslachtschromosomen, en eventuele extra chromosomen.</p>"
    },
    {
      "order": 3,
      "type": "text",
      "text": "<p>Maranja heeft, net als veel andere mensen met 18p-tetrasomie, een opening tussen de twee hartkamers. Hierdoor stroomt bloed van de ene hartkamer naar de andere.</p>"
    },
    {
      "order": 4,
      "type": "text",
      "text": "<p>Maranja kan geen vaste voeding eten omdat ze niet kan slikken. Via een maagsonde wordt haar voeding direct in de maag gebracht (afbeelding 2). Maranja's moeder pureert groenten, fruit en vlees. Door de juiste hoeveelheid water toe te voegen is het geschikt als sondevoeding</p><p>De vertering van zetmeel uit de sondevoeding begint bij Maranja pas in de twaalfvingerige darm.<br>Zelfs al zou speeksel van Maranja in haar maag komen, dan zouden de speekselenzymen daar zetmeel niet of nauwelijks kunnen verteren.</p>"
    },
    {
      "order": 5,
      "type": "image",
      "media_path": "media/in-exam/img_cc5fe90dcfbf.png",
      "azure_url": "https://bbprodpublicsa.blob.core.windows.net/public/e0ee1930bdfc4ee791081a812399115c.png",
      "caption": ""
    }
  ],
  "bijlages": []
}