{
  "id": "vwo_frans_2025_t1_q09",
  "metadata": {
    "exam": {
      "education_level": "vwo",
      "discipline": "frans",
      "year": 2025,
      "tijdvak": 1
    },
    "curriculum": {
      "education_level_discipline_id": 18,
      "domains": [],
      "subdomains": [],
      "sub_learning_objective_ids": []
    }
  },
  "question": {
    "text": "<p>Qu'est-ce qui est vrai d'après le dernier alinéa ?<br>A L'apéritif dînatoire est surtout apprécié par les jeunes adultes.<br>B Les 18-30 ans accordent beaucoup de valeur à un repas équilibré.<br>C Pendant un apéritif dînatoire on boit moins que d'habitude.<br>D Prendre l'apéro est un rituel qui se fait fréquemment entre voisins.</p>",
    "max_score": 1,
    "is_self_scored": false
  },
  "solution": {
    "text": "",
    "image": null
  },
  "content_context": [],
  "bijlages": [
    {
      "name": "frans bijlage 2025.pdf",
      "media_path": "media/bijlages/frans_bijlage_2025_6d51bbb83a9e.pdf",
      "azure_url": "https://bbprodpublicsa.blob.core.windows.net/public/eed8ec0ce9264b4987cb65e409f4d7b8.pdf"
    }
  ]
}